[
  {
    "name": "\u30db\u30c6\u30eb\u30cb\u30e5\u30fc\u30c8\u30ea\u30ce",
    "artist": "THE YELLOW MONKEY",
    "id": "66j7OAinOnLbkATzcQPfmA",
    "added_at": "2024-01-08T10:26:31Z",
    "added_by": "goobz24",
    "length_seconds": 244
  },
  {
    "name": "YOU&\u611bHeaven",
    "artist": "ano",
    "id": "61y30C7o99Zi0uGCyB5vqy",
    "added_at": "2024-01-08T10:29:18Z",
    "added_by": "goobz24",
    "length_seconds": 225
  },
  {
    "name": "\u30a2\u30f3\u30c1\u30b3\u30f3\u30d5\u30a3\u30c1\u30e5\u30fc\u30eb",
    "artist": "\u2260ME",
    "id": "0SFKu7LtAyBooZ75n0vPf7",
    "added_at": "2024-01-08T10:33:35Z",
    "added_by": "goobz24",
    "length_seconds": 253
  },
  {
    "name": "Say My Name",
    "artist": "HEY-SMITH",
    "id": "06YNVx8q2zF84s8SfGbxMC",
    "added_at": "2024-01-14T07:49:50Z",
    "added_by": "goobz24",
    "length_seconds": 108
  },
  {
    "name": "Hands Up",
    "artist": "NCT WISH",
    "id": "0Wp5yopFqgKyklOReg9S8a",
    "added_at": "2024-01-14T07:50:16Z",
    "added_by": "goobz24",
    "length_seconds": 194
  },
  {
    "name": "Candy Kiss",
    "artist": "Travis Japan",
    "id": "5KrJaDiB7WKUrkPOWUuxJp",
    "added_at": "2024-01-17T13:02:35Z",
    "added_by": "goobz24",
    "length_seconds": 201
  },
  {
    "name": "Show",
    "artist": "Ado",
    "id": "1rDgAHDX95RmylxjgVW9tN",
    "added_at": "2024-01-22T11:34:27Z",
    "added_by": "goobz24",
    "length_seconds": 189
  },
  {
    "name": "Magic",
    "artist": "Mrs. GREEN APPLE",
    "id": "2ny5O2JHnrb79I1hQcFBBn",
    "added_at": "2024-01-22T11:59:04Z",
    "added_by": "goobz24",
    "length_seconds": 263
  },
  {
    "name": "Subtitle",
    "artist": "OFFICIAL HIGE DANDISM",
    "id": "4zrKPIygugUDKGFEjVwpSB",
    "added_at": "2024-01-22T12:06:07Z",
    "added_by": "goobz24",
    "length_seconds": 305
  },
  {
    "name": "\u30c0\u30f3\u30b9\u30db\u30fc\u30eb",
    "artist": "Mrs. GREEN APPLE",
    "id": "0ddRamsLtRHHRiyWBmXk1c",
    "added_at": "2024-01-22T12:11:18Z",
    "added_by": "goobz24",
    "length_seconds": 203
  },
  {
    "name": "My Best Friend -Live on 2017.9.18-",
    "artist": "Little Glee Monster",
    "id": "2GWuyVBFi9cS9FwBUMhyVV",
    "added_at": "2024-01-24T11:13:35Z",
    "added_by": "goobz24",
    "length_seconds": 317
  },
  {
    "name": "\u304d\u3063\u3068\u306d\uff01",
    "artist": "\u4e2d\u6751\u4f73\u7a42",
    "id": "1aleydUWuiBfdhxe8CMyV1",
    "added_at": "2024-01-24T11:14:35Z",
    "added_by": "goobz24",
    "length_seconds": 246
  },
  {
    "name": "\u30ea\u30f3\u30c0\u30ea\u30f3\u30c0",
    "artist": "\u30b6\u30fb\u9752\u6625\u30ed\u30c3\u30af\u30b9",
    "id": "4WxWBwb8PSxlNjAB4xu6U1",
    "added_at": "2024-01-24T12:03:14Z",
    "added_by": "goobz24",
    "length_seconds": 196
  },
  {
    "name": "\u6211\u611b\u4f60",
    "artist": "Cody\u30fbLee(\u674e)",
    "id": "7jXoUqjqJVQGHDBs9ZGy08",
    "added_at": "2024-01-27T06:35:25Z",
    "added_by": "goobz24",
    "length_seconds": 296
  },
  {
    "name": "\u511a\u304f\u306a\u3044",
    "artist": "SUPER BEAVER",
    "id": "4oGe0AT9wDhwHfDTifSw0e",
    "added_at": "2024-01-28T01:43:24Z",
    "added_by": "goobz24",
    "length_seconds": 310
  },
  {
    "name": "Dragon Night",
    "artist": "SEKAI NO OWARI",
    "id": "4XdzCpY4Ekv5SezuuFpBDG",
    "added_at": "2024-01-28T05:31:13Z",
    "added_by": "goobz24",
    "length_seconds": 229
  },
  {
    "name": "Hanataba no Kawari ni",
    "artist": "moon drop",
    "id": "0FviV7XOz2t94tCyjqCSpr",
    "added_at": "2024-01-28T05:33:51Z",
    "added_by": "goobz24",
    "length_seconds": 252
  },
  {
    "name": "LEVEL UP",
    "artist": "Travis Japan",
    "id": "1Hmfd8Uql1SPOXupKJOR68",
    "added_at": "2024-01-31T08:09:54Z",
    "added_by": "goobz24",
    "length_seconds": 154
  },
  {
    "name": "\u60f3\u671b",
    "artist": "Masaharu Fukuyama",
    "id": "2jTXs5PwRmPRWyJQ4lKfIR",
    "added_at": "2024-01-31T08:13:39Z",
    "added_by": "goobz24",
    "length_seconds": 264
  },
  {
    "name": "Sesame",
    "artist": "Kroi",
    "id": "1DuTUxS7cBQf2ypQipYhfM",
    "added_at": "2024-02-04T13:11:06Z",
    "added_by": "goobz24",
    "length_seconds": 212
  },
  {
    "name": "\u82b1\u306b\u306a\u3063\u3066 - Be a flower",
    "artist": "Ryokuoushoku Shakai",
    "id": "2EmkTBTh964LQen4Vz0svg",
    "added_at": "2024-02-04T13:16:39Z",
    "added_by": "goobz24",
    "length_seconds": 199
  },
  {
    "name": "Bling-Bang-Bang-Born",
    "artist": "Creepy Nuts",
    "id": "0kdqcbwei4MDWFEX5f33yG",
    "added_at": "2024-02-04T13:17:11Z",
    "added_by": "goobz24",
    "length_seconds": 168
  },
  {
    "name": "\u30ca\u30cf\u30c8\u30e0\u30b8\u30fc\u30af",
    "artist": "Mrs. GREEN APPLE",
    "id": "7sditHCsoFw3nHnjFv1BHV",
    "added_at": "2024-02-04T13:25:15Z",
    "added_by": "goobz24",
    "length_seconds": 262
  },
  {
    "name": "\u795d\u65e5",
    "artist": "Kaneko Ayano",
    "id": "12GGxP9lcUseII0JJEQ4YZ",
    "added_at": "2024-02-06T13:12:56Z",
    "added_by": "goobz24",
    "length_seconds": 258
  },
  {
    "name": "We GO",
    "artist": "Ketsumeishi",
    "id": "1qSC45sRAPzDP5y8zvDsKr",
    "added_at": "2024-02-11T12:16:39Z",
    "added_by": "goobz24",
    "length_seconds": 329
  },
  {
    "name": "Ghost and Writer",
    "artist": "WEDNESDAY CAMPANELLA",
    "id": "6axzEtdIhzPnT69BiG6RpU",
    "added_at": "2024-02-11T12:38:33Z",
    "added_by": "goobz24",
    "length_seconds": 248
  },
  {
    "name": "rhythm 64",
    "artist": "Aimyon",
    "id": "4KWMnXGQ4wCiDU1vP8uGVb",
    "added_at": "2024-02-11T12:49:19Z",
    "added_by": "goobz24",
    "length_seconds": 268
  },
  {
    "name": "KATA (feat. \u5b6bGONG)",
    "artist": "REAL-T, \u5b6bGONG",
    "id": "45F1hn2t0d01BvI5Cu6pD4",
    "added_at": "2024-02-12T12:21:32Z",
    "added_by": "goobz24",
    "length_seconds": 213
  },
  {
    "name": "Real Love",
    "artist": "TEN's UNIQUE, KAYA, JAMS ONE, BEAR B, 1LAW",
    "id": "0XsmYRbOKHgvVSfmv0qWRS",
    "added_at": "2024-02-12T12:36:21Z",
    "added_by": "goobz24",
    "length_seconds": 222
  },
  {
    "name": "Hit The Bong (feat. VOCA Luciano)",
    "artist": "Japanese Magenese, VOCA Luciano",
    "id": "0t4zUqB6R4SUKSbOIFCYEG",
    "added_at": "2024-02-12T12:37:23Z",
    "added_by": "goobz24",
    "length_seconds": 240
  },
  {
    "name": "Smoke Like a Dipset",
    "artist": "Japanese Magenese",
    "id": "68EAhfUxGFKlXE9RKFBbd9",
    "added_at": "2024-02-12T12:37:52Z",
    "added_by": "goobz24",
    "length_seconds": 198
  },
  {
    "name": "Rodeo",
    "artist": "Tohji",
    "id": "61pCeYLwoZ64af0rGWcmxh",
    "added_at": "2024-02-12T12:41:02Z",
    "added_by": "goobz24",
    "length_seconds": 135
  },
  {
    "name": "GILA GILA",
    "artist": "Awich, JP THE WAVY, YZERR",
    "id": "7AsWduh1mkB8uKOox5NH0X",
    "added_at": "2024-02-12T12:42:39Z",
    "added_by": "goobz24",
    "length_seconds": 253
  },
  {
    "name": "115\u4e07\u30ad\u30ed\u306e\u30d5\u30a3\u30eb\u30e0",
    "artist": "OFFICIAL HIGE DANDISM",
    "id": "278JqkBGkjDovOYAwE8TW7",
    "added_at": "2024-02-13T07:39:34Z",
    "added_by": "goobz24",
    "length_seconds": 324
  },
  {
    "name": "hurray",
    "artist": "Yabai T-Shirts Yasan",
    "id": "0Fv7VQdjRjTqb0wk88uBzP",
    "added_at": "2024-02-16T06:50:03Z",
    "added_by": "goobz24",
    "length_seconds": 227
  },
  {
    "name": "\u89b3\u5149",
    "artist": "Crazy Ken Band",
    "id": "4dbGhybNTNePetlWQEcJ6q",
    "added_at": "2024-02-16T06:59:08Z",
    "added_by": "goobz24",
    "length_seconds": 342
  },
  {
    "name": "US / \u30a2\u30b9",
    "artist": "Homecomings",
    "id": "1aeaftZG6Bura9j9h7GQoc",
    "added_at": "2024-02-16T07:18:11Z",
    "added_by": "goobz24",
    "length_seconds": 318
  },
  {
    "name": "Americana",
    "artist": "Banda AL9",
    "id": "1Qx7FpHH6vZMJFubYtzDZr",
    "added_at": "2024-02-20T01:41:44Z",
    "added_by": "goobz24",
    "length_seconds": 204
  },
  {
    "name": "\u5c0f\u3055\u306a\u604b\u306e\u3046\u305f",
    "artist": "MONGOL800",
    "id": "23atyJacJVHvB9RHBNhr35",
    "added_at": "2024-02-20T01:42:44Z",
    "added_by": "goobz24",
    "length_seconds": 222
  },
  {
    "name": "BROKEN GAMES",
    "artist": "FZMZ",
    "id": "77OLrw9sVVNHxnceM9q1i5",
    "added_at": "2024-02-20T01:50:07Z",
    "added_by": "goobz24",
    "length_seconds": 236
  },
  {
    "name": "PLAYING WITH FIRE",
    "artist": "BLACKPINK",
    "id": "7qmvLmX9tyaTiBAVNI6YEn",
    "added_at": "2024-02-20T02:31:31Z",
    "added_by": "goobz24",
    "length_seconds": 197
  },
  {
    "name": "What's up? Pop! (feat. \u521d\u97f3\u30df\u30af)",
    "artist": "Capchii, Hatsune Miku",
    "id": "4cTLdiBHGZbnVduyq6BqpA",
    "added_at": "2024-02-21T06:20:08Z",
    "added_by": "goobz24",
    "length_seconds": 162
  },
  {
    "name": "Boku Wa Chotto",
    "artist": "Haruomi Hosono, Mac DeMarco",
    "id": "1RMnWyL9KlDgmAhirqNxin",
    "added_at": "2024-02-23T02:53:07Z",
    "added_by": "goobz24",
    "length_seconds": 171
  },
  {
    "name": "Dream Chaser (feat. BIM)",
    "artist": "kZm, BIM",
    "id": "43a7yPJ1LoEs0TlpPaeReS",
    "added_at": "2024-03-03T05:07:24Z",
    "added_by": "goobz24",
    "length_seconds": 194
  },
  {
    "name": "Burrito",
    "artist": "Ilke-Ta",
    "id": "45UWrwrej1Krgd5b0IkVrD",
    "added_at": "2024-03-03T09:51:46Z",
    "added_by": "goobz24",
    "length_seconds": 145
  },
  {
    "name": "Burger Bacha",
    "artist": "T-toe, Sibel",
    "id": "79R7eqzDvMXC29HRWfK2SX",
    "added_at": "2024-03-03T10:22:48Z",
    "added_by": "goobz24",
    "length_seconds": 326
  },
  {
    "name": "Kibutz Jungle",
    "artist": "Dos Kanye",
    "id": "1Nbw4wdra504ilpEvR2try",
    "added_at": "2024-03-03T10:26:23Z",
    "added_by": "goobz24",
    "length_seconds": 360
  },
  {
    "name": "\u307e\u305f\u9022\u3046\u65e5\u307e\u3067",
    "artist": "Kiyohiko Ozaki",
    "id": "6S64OnWDB6YTKPKJkwN0oE",
    "added_at": "2024-03-05T15:42:28Z",
    "added_by": "goobz24",
    "length_seconds": 174
  },
  {
    "name": "\u4e16\u754c\u304c\u7d42\u308b\u307e\u3067\u306f\u2026 [WANDS \u7b2c5\u671f ver.]",
    "artist": "WANDS",
    "id": "3Kihz14e1cNkpl5PiJOiB7",
    "added_at": "2024-03-07T07:54:51Z",
    "added_by": "goobz24",
    "length_seconds": 313
  },
  {
    "name": "\u4eba\u751f\u306f\u5922\u3060\u3089\u3051",
    "artist": "Sheena Ringo",
    "id": "0z2xgbxkLvrpzBZDtYIIXS",
    "added_at": "2024-03-07T12:06:59Z",
    "added_by": "goobz24",
    "length_seconds": 194
  },
  {
    "name": "\u591c\u9593\u98db\u884c",
    "artist": "Junko Yagami",
    "id": "1JuTkU549nkpxQY6JUpBVV",
    "added_at": "2024-03-09T13:22:12Z",
    "added_by": "goobz24",
    "length_seconds": 383
  },
  {
    "name": "I remember you",
    "artist": "YUI",
    "id": "5HD2MrQAgKWXnziVGsMVUv",
    "added_at": "2024-03-09T14:07:47Z",
    "added_by": "goobz24",
    "length_seconds": 248
  },
  {
    "name": "BE FREE",
    "artist": "GReeeeN",
    "id": "05lIPRPv5UJu1yM0PHKGeH",
    "added_at": "2024-03-09T15:11:17Z",
    "added_by": "goobz24",
    "length_seconds": 278
  },
  {
    "name": "\u9583\u5149 - feat.10-FEET [2020 Remaster]",
    "artist": "Tokyo Ska Paradise Orchestra, 10-FEET",
    "id": "2TJitpzEXzGzrziWL5rNsc",
    "added_at": "2024-03-14T02:05:09Z",
    "added_by": "goobz24",
    "length_seconds": 404
  },
  {
    "name": "TANGTANG",
    "artist": "kudaranai1nichi",
    "id": "5ds1g5gdck4Y4HsoOXo8cz",
    "added_at": "2024-03-21T09:49:11Z",
    "added_by": "goobz24",
    "length_seconds": 180
  },
  {
    "name": "Bouquet",
    "artist": "TRACK15",
    "id": "2nmKXcHdicY328zAPkcSJB",
    "added_at": "2024-03-21T09:49:40Z",
    "added_by": "goobz24",
    "length_seconds": 238
  },
  {
    "name": "Prepare Yourself!",
    "artist": "\u30b5\u30d0\u30b7\u30b9\u30bf\u30fc",
    "id": "0vBPojhtgWvIZORtXr0Nl4",
    "added_at": "2024-03-21T09:50:18Z",
    "added_by": "goobz24",
    "length_seconds": 234
  },
  {
    "name": "\u30d6\u30fc\u30d3\u30fc\u30fb\u30d7\u30e9\u30a4\u30ba",
    "artist": "\u548c\u306c\u304b",
    "id": "3Erbx18R75nXl4bqkxANVs",
    "added_at": "2024-03-25T06:24:27Z",
    "added_by": "goobz24",
    "length_seconds": 241
  },
  {
    "name": "\u6674\u308b",
    "artist": "\u30e8\u30eb\u30b7\u30ab",
    "id": "5eY7692tmgHB9dbmq6wa2M",
    "added_at": "2024-03-26T16:38:20Z",
    "added_by": "goobz24",
    "length_seconds": 270
  },
  {
    "name": "\u9752\u3068\u590f - Remastered 2020",
    "artist": "Mrs. GREEN APPLE",
    "id": "16E75VP5FKLoKDrOR0ulZ3",
    "added_at": "2024-03-28T03:59:06Z",
    "added_by": "goobz24",
    "length_seconds": 273
  },
  {
    "name": "\u305d\u3093\u306abitter\u306a\u8a71",
    "artist": "Vaundy",
    "id": "4QlSFkbRxZWkHDF1MqBaEY",
    "added_at": "2024-03-28T04:00:06Z",
    "added_by": "goobz24",
    "length_seconds": 276
  },
  {
    "name": "\u3080\u3052\u3093\u3060\u3044\u3059\u304d",
    "artist": "iLiFE!",
    "id": "4hy6PxpMX6C8VHQFUuzTcI",
    "added_at": "2024-04-03T12:18:46Z",
    "added_by": "goobz24",
    "length_seconds": 217
  },
  {
    "name": "\u3069\u308a\u30fc\u307f\u3093\u30d1\u30b9\u30dd\u30fc\u30c8",
    "artist": "maidreamin",
    "id": "6gG6eYDoEGtebibBvokPs0",
    "added_at": "2024-04-04T02:08:06Z",
    "added_by": "goobz24",
    "length_seconds": 233
  }
]